skfem/__init__.py
skfem-0.0.0.dist-info/METADATA
skfem-0.0.0.dist-info/WHEEL
skfem-0.0.0.dist-info/top_level.txt
skfem-0.0.0.dist-info/RECORD
