Metadata-Version: 2.1
Name: skfem
Version: 0.0.0
Summary: Install scikit-fem instead of skfem.
Author: Tom Gustafsson
